tornado_http_auth.py
tornado_http_auth-1.1.1.dist-info/DESCRIPTION.rst
tornado_http_auth-1.1.1.dist-info/METADATA
tornado_http_auth-1.1.1.dist-info/RECORD
tornado_http_auth-1.1.1.dist-info/WHEEL
tornado_http_auth-1.1.1.dist-info/metadata.json
tornado_http_auth-1.1.1.dist-info/top_level.txt
