Metadata-Version: 2.0
Name: tornado-http-auth
Version: 1.1.1
Summary: Digest and basic authentication for tornado
Home-page: https://github.com/gvalkov/tornado-http-auth
Author: Georgi Valkov
Author-email: georgi.t.valkov@gmail.com
License: Apache License 2.0
Keywords: tornado digest-auth basic-auth
Platform: UNKNOWN
Classifier: Development Status :: 5 - Production/Stable
Classifier: Programming Language :: Python :: 2.7
Classifier: Programming Language :: Python :: 3
Classifier: License :: OSI Approved :: Apache Software License
Classifier: Intended Audience :: Developers
Requires-Dist: tornado (>=4.0.0)
